misalignment/__init__.py
misalignment/misalignment.py
misalignment-0.1.dist-info/METADATA
misalignment-0.1.dist-info/WHEEL
misalignment-0.1.dist-info/top_level.txt
misalignment-0.1.dist-info/RECORD
